polars_hist_db/__init__.py
polars_hist_db/config/__init__.py
polars_hist_db/config/config.py
polars_hist_db/config/dataset.py
polars_hist_db/config/engine.py
polars_hist_db/config/fn_builtins.py
polars_hist_db/config/helpers.py
polars_hist_db/config/input/__init__.py
polars_hist_db/config/input/dsv_crawler.py
polars_hist_db/config/input/ingest_fn_registry.py
polars_hist_db/config/input/input_source.py
polars_hist_db/config/input/jetstream_config.py
polars_hist_db/config/input/nats_config.py
polars_hist_db/config/input/types.py
polars_hist_db/config/parser.py
polars_hist_db/config/parser_config.py
polars_hist_db/config/table.py
polars_hist_db/config/transform_fn_registry.py
polars_hist_db/core/__init__.py
polars_hist_db/core/audit.py
polars_hist_db/core/audit_log_tracker.py
polars_hist_db/core/dataframe.py
polars_hist_db/core/db.py
polars_hist_db/core/delta_table.py
polars_hist_db/core/table.py
polars_hist_db/core/table_config.py
polars_hist_db/core/timehint.py
polars_hist_db/dataset/__init__.py
polars_hist_db/dataset/entrypoint.py
polars_hist_db/dataset/extract_item.py
polars_hist_db/dataset/foreign_key_helper.py
polars_hist_db/dataset/primary_item.py
polars_hist_db/dataset/scrape.py
polars_hist_db/loaders/__init__.py
polars_hist_db/loaders/dsv/__init__.py
polars_hist_db/loaders/dsv/dsv_loader.py
polars_hist_db/loaders/dsv/file_search.py
polars_hist_db/loaders/dsv/ziptools.py
polars_hist_db/loaders/dsv_input_source.py
polars_hist_db/loaders/ingest_payload.py
polars_hist_db/loaders/input_source.py
polars_hist_db/loaders/input_source_factory.py
polars_hist_db/loaders/jetstream/__init__.py
polars_hist_db/loaders/jetstream/nats_client.py
polars_hist_db/loaders/jetstream_input_source.py
polars_hist_db/loaders/transform.py
polars_hist_db/logging.yaml
polars_hist_db/py.typed
polars_hist_db/scripts/__init__.py
polars_hist_db/scripts/drop_dataset_tables.py
polars_hist_db/scripts/init_helpers.py
polars_hist_db/scripts/scrape_dataset.py
polars_hist_db/types.py
polars_hist_db-0.8.23.dist-info/LICENSE
polars_hist_db-0.8.23.dist-info/METADATA
polars_hist_db-0.8.23.dist-info/WHEEL
polars_hist_db-0.8.23.dist-info/entry_points.txt
polars_hist_db-0.8.23.dist-info/RECORD
