Metadata-Version: 2.3
Name: polars-hist-db
Version: 0.8.23
Summary: (dsv,jetstream) --> dataframe <--> bitemporal-tables
Author: jr200
Author-email: jayshan+git@gmail.com
Requires-Python: >=3.12,<4.0
Classifier: Programming Language :: Python :: 3
Classifier: Programming Language :: Python :: 3.12
Classifier: Programming Language :: Python :: 3.13
Provides-Extra: nats
Provides-Extra: sqlachemy
Requires-Dist: nats-py (>=2.11.0,<3.0.0) ; extra == "nats"
Requires-Dist: pandas (>=2.3.0,<3.0.0)
Requires-Dist: polars[sqlachemy] (>=1.32.3,<2.0.0) ; extra == "sqlachemy"
Requires-Dist: pyarrow (>=21.0.0,<22.0.0)
Requires-Dist: pymysql (>=1.1.2,<2.0.0)
Requires-Dist: pytz (>=2025.2,<2026.0)
Requires-Dist: pyyaml (>=6.0.2,<7.0.0)
Requires-Dist: scandir-rs (==2.8.0)
Requires-Dist: sql-metadata (>=2.17.0,<3.0.0)
Requires-Dist: sqlalchemy[asyncio] (>=2.0.43,<3.0.0)
Project-URL: Repository, https://github.com/jr200/polars-hist-db
